newclid/__init__.py
newclid/__main__.py
newclid/_lazy_loading.py
newclid/api.py
newclid/combinatorics.py
newclid/configs.py
newclid/geometry.py
newclid/listing.py
newclid/match_theorems.py
newclid/points_manipulation.py
newclid/predicates.py
newclid/pretty.py
newclid/problem.py
newclid/proof.py
newclid/proof_writing.py
newclid/ratios.py
newclid/run_loop.py
newclid/symbols_graph.py
newclid/theorem.py
newclid/trace_back.py
newclid/agent/__init__.py
newclid/agent/agents_interface.py
newclid/agent/breadth_first_search.py
newclid/agent/human_agent.py
newclid/agent/registry.py
newclid/default_configs/defs.txt
newclid/default_configs/legacy_defs.txt
newclid/default_configs/new_rules.txt
newclid/default_configs/rules.txt
newclid/defs/__init__.py
newclid/defs/clause.py
newclid/defs/definition.py
newclid/dependencies/__init__.py
newclid/dependencies/caching.py
newclid/dependencies/dependency.py
newclid/dependencies/dependency_building.py
newclid/dependencies/why_graph.py
newclid/dependencies/why_predicates.py
newclid/numerical/__init__.py
newclid/numerical/angles.py
newclid/numerical/check.py
newclid/numerical/distances.py
newclid/numerical/draw_figure.py
newclid/numerical/geometries.py
newclid/numerical/sketch.py
newclid/reasoning_engines/__init__.py
newclid/reasoning_engines/engines_interface.py
newclid/reasoning_engines/formulas.py
newclid/reasoning_engines/algebraic_reasoning/__init__.py
newclid/reasoning_engines/algebraic_reasoning/algebraic_manipulator.py
newclid/reasoning_engines/algebraic_reasoning/geometric_tables.py
newclid/statements/__init__.py
newclid/statements/adder.py
newclid/statements/checker.py
newclid/statements/enumerator.py
newclid/statements/handler.py
newclid/statements/statement.py
newclid-2.0.2.dist-info/LICENSE
newclid-2.0.2.dist-info/METADATA
newclid-2.0.2.dist-info/WHEEL
newclid-2.0.2.dist-info/entry_points.txt
newclid-2.0.2.dist-info/top_level.txt
newclid-2.0.2.dist-info/RECORD
