Metadata-Version: 2.1
Name: newclid
Version: 2.0.2
Summary: Symbolic solver for geometric problems.
Author-email: Mathis Federico <mathfederico@gmail.com>
Classifier: Intended Audience :: Science/Research
Classifier: Intended Audience :: Developers
Classifier: Topic :: Software Development
Classifier: Topic :: Scientific/Engineering
Classifier: Operating System :: Microsoft :: Windows
Classifier: Operating System :: POSIX
Classifier: Operating System :: Unix
Classifier: Operating System :: MacOS
Requires-Python: >=3.9
License-File: LICENSE
Requires-Dist: numpy>=1.23.5
Requires-Dist: matplotlib>=3.7.0
Requires-Dist: scipy>=1.10.0
Requires-Dist: networkx
Requires-Dist: pyvis
Requires-Dist: seaborn
Requires-Dist: colorama
Requires-Dist: typing-extensions
Provides-Extra: dev
Requires-Dist: black; extra == "dev"
Requires-Dist: ruff; extra == "dev"
Requires-Dist: pytest; extra == "dev"
Requires-Dist: pytest-cov; extra == "dev"
Requires-Dist: pytest-check; extra == "dev"
Requires-Dist: pytest-mock; extra == "dev"
Requires-Dist: pre-commit; extra == "dev"
Provides-Extra: doc
Requires-Dist: numpy; extra == "doc"
Requires-Dist: sphinx-autoapi; extra == "doc"
Requires-Dist: autoapi; extra == "doc"
Requires-Dist: sphinx-rtd-theme; extra == "doc"
Requires-Dist: sphinx-autodoc-typehints; extra == "doc"
